{"tags":["permalink"],"posts":[{"title":"Post without language","url":"https://www.webmanajemen.com/no-language-permalink.html","date":"2023-07-15T04:46:44.000Z"},{"title":"Post without language and permalink","url":"https://www.webmanajemen.com/no-language.html","date":"2023-07-15T04:46:44.000Z"},{"title":"Hello World","url":"https://www.webmanajemen.com/en/Hello-World.html","date":"2023-07-15T12:20:12.639Z"},{"title":"Hello World","url":"https://www.webmanajemen.com/id/Hello-World.html","date":"2023-07-15T12:20:16.467Z"},{"title":"Hello World","url":"https://www.webmanajemen.com/zh-CN/Hello-World.html","date":"2023-07-15T12:20:19.467Z"}],"categories":["guide"]}